tests/__init__.py
tests/test.py
text_generator/__init__.py
text_generator/main.py
random_text_generator-1.1.0.dist-info/AUTHORS.md
random_text_generator-1.1.0.dist-info/LICENSE
random_text_generator-1.1.0.dist-info/METADATA
random_text_generator-1.1.0.dist-info/WHEEL
random_text_generator-1.1.0.dist-info/top_level.txt
random_text_generator-1.1.0.dist-info/RECORD
