Metadata-Version: 2.1
Name: random-text-generator
Version: 1.1.0
Summary: Generate short, simple text codes
Home-page: https://github.com/LokotamaTheMastermind/code-generator-using-python
Author: LokotamaTheMastermind
Author-email: lokotamathemastermind2@gmail.com
License: UNKNOWN
Download-URL: https://github.com/LokotamaTheMastermind/code-generator-using-python
Keywords: python,generator,code,encode,decode,random
Platform: UNKNOWN
Requires-Python: >=3.0
Requires-Dist: random-string
Requires-Dist: url64
